amberelectric/__init__.py
amberelectric/api/__init__.py
amberelectric/api/amber_api.py
amberelectric/api_client.py
amberelectric/api_response.py
amberelectric/configuration.py
amberelectric/exceptions.py
amberelectric/models/__init__.py
amberelectric/models/actual_interval.py
amberelectric/models/actual_renewable.py
amberelectric/models/advanced_price.py
amberelectric/models/base_interval.py
amberelectric/models/base_renewable.py
amberelectric/models/channel.py
amberelectric/models/channel_type.py
amberelectric/models/current_interval.py
amberelectric/models/current_renewable.py
amberelectric/models/forecast_interval.py
amberelectric/models/forecast_renewable.py
amberelectric/models/interval.py
amberelectric/models/price_descriptor.py
amberelectric/models/range.py
amberelectric/models/renewable.py
amberelectric/models/renewable_descriptor.py
amberelectric/models/site.py
amberelectric/models/site_status.py
amberelectric/models/spike_status.py
amberelectric/models/tariff_information.py
amberelectric/models/usage.py
amberelectric/py.typed
amberelectric/rest.py
amberelectric-2.0.11.dist-info/LICENSE
amberelectric-2.0.11.dist-info/METADATA
amberelectric-2.0.11.dist-info/WHEEL
amberelectric-2.0.11.dist-info/RECORD
