Metadata-Version: 2.1
Name: amberelectric
Version: 2.0.11
Summary: Amber Electric Public API
Home-page: https://github.com/GIT_USER_ID/GIT_REPO_ID
License: Apache Software License
Keywords: OpenAPI,OpenAPI-Generator,Amber Electric Public API
Author: Amber Electric Development Team
Author-email: dev@amber.com.au
Requires-Python: >=3.7,<4.0
Classifier: License :: Other/Proprietary License
Classifier: Programming Language :: Python :: 3
Classifier: Programming Language :: Python :: 3.7
Classifier: Programming Language :: Python :: 3.8
Classifier: Programming Language :: Python :: 3.9
Classifier: Programming Language :: Python :: 3.10
Classifier: Programming Language :: Python :: 3.11
Classifier: Programming Language :: Python :: 3.12
Classifier: Programming Language :: Python :: 3.13
Requires-Dist: aenum (>=3.1.11)
Requires-Dist: pydantic (>=1.10.5)
Requires-Dist: python-dateutil (>=2.8.2)
Requires-Dist: urllib3 (>=1.25.3)
Project-URL: Repository, https://github.com/GIT_USER_ID/GIT_REPO_ID
